MANIFEST.in
README.rst
setup.py
docs/HISTORY.txt
docs/LICENSE.txt
docs/graph_model.png
emencia/__init__.py
emencia.django.newsletter.egg-info/PKG-INFO
emencia.django.newsletter.egg-info/SOURCES.txt
emencia.django.newsletter.egg-info/dependency_links.txt
emencia.django.newsletter.egg-info/entry_points.txt
emencia.django.newsletter.egg-info/namespace_packages.txt
emencia.django.newsletter.egg-info/not-zip-safe
emencia.django.newsletter.egg-info/requires.txt
emencia.django.newsletter.egg-info/top_level.txt
emencia/django/__init__.py
emencia/django/newsletter/__init__.py
emencia/django/newsletter/context_processors.py
emencia/django/newsletter/forms.py
emencia/django/newsletter/mailer.py
emencia/django/newsletter/managers.py
emencia/django/newsletter/models.py
emencia/django/newsletter/settings.py
emencia/django/newsletter/tests.py
emencia/django/newsletter/testsettings.py
emencia/django/newsletter/admin/__init__.py
emencia/django/newsletter/admin/contact.py
emencia/django/newsletter/admin/mailinglist.py
emencia/django/newsletter/admin/newsletter.py
emencia/django/newsletter/admin/smtpserver.py
emencia/django/newsletter/admin/workgroup.py
emencia/django/newsletter/locale/de/LC_MESSAGES/django.mo
emencia/django/newsletter/locale/de/LC_MESSAGES/django.po
emencia/django/newsletter/locale/en/LC_MESSAGES/django.mo
emencia/django/newsletter/locale/en/LC_MESSAGES/django.po
emencia/django/newsletter/locale/es/LC_MESSAGES/django.mo
emencia/django/newsletter/locale/es/LC_MESSAGES/django.po
emencia/django/newsletter/locale/fr/LC_MESSAGES/django.mo
emencia/django/newsletter/locale/fr/LC_MESSAGES/django.po
emencia/django/newsletter/locale/it/LC_MESSAGES/django.mo
emencia/django/newsletter/locale/it/LC_MESSAGES/django.po
emencia/django/newsletter/locale/ja/LC_MESSAGES/django.mo
emencia/django/newsletter/locale/ja/LC_MESSAGES/django.po
emencia/django/newsletter/locale/nl/LC_MESSAGES/django.mo
emencia/django/newsletter/locale/nl/LC_MESSAGES/django.po
emencia/django/newsletter/locale/pt/LC_MESSAGES/django.mo
emencia/django/newsletter/locale/pt/LC_MESSAGES/django.po
emencia/django/newsletter/locale/zh_CN/LC_MESSAGES/django.mo
emencia/django/newsletter/locale/zh_CN/LC_MESSAGES/django.po
emencia/django/newsletter/management/__init__.py
emencia/django/newsletter/management/commands/__init__.py
emencia/django/newsletter/management/commands/send_newsletter.py
