Metadata-Version: 1.0
Name: emencia.django.newsletter
Version: 0.2
Summary: A Django app for sending newsletter by email to a contact list.
Home-page: http://emencia.fr
Author: Fantomas42
Author-email: fantomas42@gmail.com
License: BSD License
Keywords: django,newsletter,mailing
Platform: UNKNOWN
Classifier: Intended Audience :: Developers
Classifier: Operating System :: OS Independent
Classifier: Programming Language :: Python
Classifier: Topic :: Software Development :: Libraries :: Python Modules
Classifier: License :: OSI Approved :: BSD License
Classifier: Framework :: Django
